INSTALL.markdown
MANIFEST.in
README.markdown
setup.py
bin/projectenv.csh
bin/projectenv.sh
projectenv/__init__.py
projectenv/__main__.py
projectenv/cmdrunner.py
projectenv/commands.py
projectenv/logger.py
projectenv/package_manager.py
projectenv/scriptgen.py
projectenv/spec_helpers.py
projectenv.egg-info/PKG-INFO
projectenv.egg-info/SOURCES.txt
projectenv.egg-info/dependency_links.txt
projectenv.egg-info/top_level.txt
specs/default.py