Metadata-Version: 1.0
Name: projectenv
Version: 0.0.7
Summary: The easiest way to create virtual environments for your python projects
Home-page: https://github.com/teaminsight/projectenv
Author: Jordan Bach
Author-email: jordanbach@gmail.com
License: UNKNOWN
Platform: UNKNOWN
